gmtds_client/__init__.py
gmtds_client-0.0.1.dist-info/METADATA
gmtds_client-0.0.1.dist-info/WHEEL
gmtds_client-0.0.1.dist-info/RECORD
